{
  "path": "bmm150",
  "example": {
    "name": "The BMM150 is a standalone geomagnetic sensor for consumer market applications. It allows measurements of the magnetic field in three perpendicular axes. Based on Bosch's proprietary FlipCore technology, performance and features of BMM150 are carefully tuned and perfectly match the demanding requirements of all 3-axis mobile applications such as electronic compass, navigation or augmented reality.",
    "category": [
      "UPM"
    ],
    "platform": {
      "boards": [
        "arduino_101",
        "arduino_101_sss"
      ]
    }
  }
}
